1_getting_started/counter.sv
module counter ( input logic clk,
                 input logic reset,
                 output logic[7:0] count );

  always_ff @(posedge clk)
  begin
    if (reset == 1) begin
      count <= 0;
    end
    else begin
      count <= count + 1;
    end
  end

endmodule

1_getting_started/counter_test.sv
`timescale 1ns/1ns // 1 tick is 1ns; use 1ns resolution (since we're not simulating wire delays or anything)

module counter_enable_test;

  // Declare the signals that will connect to our device under test (DUT)
  logic clk = 0;
  logic reset;
  logic[7:0] count;
  
  // Instantiate and connect the DUT
  counter dut(.clk(clk),
              .reset(reset),
              .count(count));
  
  // Create the clock signal
  always #5 clk = ~clk;

  // Now run the test!
  initial begin
    // Dump all of the signals in the design to the VCD file which we can view with GTKwave
    $dumpfile("counter.vcd");
    $dumpvars(0, dut); // Dump all of the signals in the DUT


    $display("Beginning of counter test...");

    $display("(reset asserted)" );
    reset = 1;
    #27; // Wait for a few clock cycles

    // Check that the counter is reset correctly 
    assert(count == 0) else $error("Counter not reset: expected 0 but got %d !", count);

    $display("(reset released)" );
    reset = 0;

    @(posedge clk); // Wait for the next rising edge
    @(negedge clk); // and a little past so we have the values

    // Check that the counter has incremented
    assert(count == 1) else $error("Counter did not increment: expected 1 but got %d !", count);

    // We could keep checking other things here; instead we'll just wait for a microsecond
    // so that the waveform captures a good bit of time.
    #1000

    $display("Test complete!");
    $finish; // End the simulation (even though the clock is still going
  end

endmodule

1_getting_started/counter.vcd
$date
	Tue Apr 09 14:24:20 2024
$end
$version
	Icarus Verilog
$end
$timescale
	1ns
$end
$scope module counter_enable_test $end
$scope module dut $end
$var wire 1 ! clk $end
$var wire 1 " reset $end
$var reg 8 # count [7:0] $end
$upscope $end
$upscope $end
$enddefinitions $end
$comment Show the parameter values. $end
$dumpall
$end
#0
$dumpvars
bx #
1"
0!
$end
#5
b0 #
1!
#10
0!
#15
1!
#20
0!
#25
1!
#27
0"
#30
0!
#35
b1 #
1!
#40
0!
#45
b10 #
1!
#50
0!
#55
b11 #
1!
#60
0!
#65
b100 #
1!
#70
0!
#75
b101 #
1!
#80
0!
#85
b110 #
1!
#90
0!
#95
b111 #
1!
#100
0!
#105
b1000 #
1!
#110
0!
#115
b1001 #
1!
#120
0!
#125
b1010 #
1!
#130
0!
#135
b1011 #
1!
#140
0!
#145
b1100 #
1!
#150
0!
#155
b1101 #
1!
#160
0!
#165
b1110 #
1!
#170
0!
#175
b1111 #
1!
#180
0!
#185
b10000 #
1!
#190
0!
#195
b10001 #
1!
#200
0!
#205
b10010 #
1!
#210
0!
#215
b10011 #
1!
#220
0!
#225
b10100 #
1!
#230
0!
#235
b10101 #
1!
#240
0!
#245
b10110 #
1!
#250
0!
#255
b10111 #
1!
#260
0!
#265
b11000 #
1!
#270
0!
#275
b11001 #
1!
#280
0!
#285
b11010 #
1!
#290
0!
#295
b11011 #
1!
#300
0!
#305
b11100 #
1!
#310
0!
#315
b11101 #
1!
#320
0!
#325
b11110 #
1!
#330
0!
#335
b11111 #
1!
#340
0!
#345
b100000 #
1!
#350
0!
#355
b100001 #
1!
#360
0!
#365
b100010 #
1!
#370
0!
#375
b100011 #
1!
#380
0!
#385
b100100 #
1!
#390
0!
#395
b100101 #
1!
#400
0!
#405
b100110 #
1!
#410
0!
#415
b100111 #
1!
#420
0!
#425
b101000 #
1!
#430
0!
#435
b101001 #
1!
#440
0!
#445
b101010 #
1!
#450
0!
#455
b101011 #
1!
#460
0!
#465
b101100 #
1!
#470
0!
#475
b101101 #
1!
#480
0!
#485
b101110 #
1!
#490
0!
#495
b101111 #
1!
#500
0!
#505
b110000 #
1!
#510
0!
#515
b110001 #
1!
#520
0!
#525
b110010 #
1!
#530
0!
#535
b110011 #
1!
#540
0!
#545
b110100 #
1!
#550
0!
#555
b110101 #
1!
#560
0!
#565
b110110 #
1!
#570
0!
#575
b110111 #
1!
#580
0!
#585
b111000 #
1!
#590
0!
#595
b111001 #
1!
#600
0!
#605
b111010 #
1!
#610
0!
#615
b111011 #
1!
#620
0!
#625
b111100 #
1!
#630
0!
#635
b111101 #
1!
#640
0!
#645
b111110 #
1!
#650
0!
#655
b111111 #
1!
#660
0!
#665
b1000000 #
1!
#670
0!
#675
b1000001 #
1!
#680
0!
#685
b1000010 #
1!
#690
0!
#695
b1000011 #
1!
#700
0!
#705
b1000100 #
1!
#710
0!
#715
b1000101 #
1!
#720
0!
#725
b1000110 #
1!
#730
0!
#735
b1000111 #
1!
#740
0!
#745
b1001000 #
1!
#750
0!
#755
b1001001 #
1!
#760
0!
#765
b1001010 #
1!
#770
0!
#775
b1001011 #
1!
#780
0!
#785
b1001100 #
1!
#790
0!
#795
b1001101 #
1!
#800
0!
#805
b1001110 #
1!
#810
0!
#815
b1001111 #
1!
#820
0!
#825
b1010000 #
1!
#830
0!
#835
b1010001 #
1!
#840
0!
#845
b1010010 #
1!
#850
0!
#855
b1010011 #
1!
#860
0!
#865
b1010100 #
1!
#870
0!
#875
b1010101 #
1!
#880
0!
#885
b1010110 #
1!
#890
0!
#895
b1010111 #
1!
#900
0!
#905
b1011000 #
1!
#910
0!
#915
b1011001 #
1!
#920
0!
#925
b1011010 #
1!
#930
0!
#935
b1011011 #
1!
#940
0!
#945
b1011100 #
1!
#950
0!
#955
b1011101 #
1!
#960
0!
#965
b1011110 #
1!
#970
0!
#975
b1011111 #
1!
#980
0!
#985
b1100000 #
1!
#990
0!
#995
b1100001 #
1!
#1000
0!
#1005
b1100010 #
1!
#1010
0!
#1015
b1100011 #
1!
#1020
0!
#1025
b1100100 #
1!
#1030
0!
#1035
b1100101 #
1!
