2_alu_only/progmem.sv
// Program memory implemented as combinational logic
// On the iCE40, this will be implemented in the logic fabric

// This is only used for the single-cycle machine; once we move to the
// multi-cycle design we will have a unified (and clocked) memory.

module progmem(input logic[31:0] addr,
               output logic[31:0] instr);

    // In the future, we will implement this by reading instructions stored in
    // an external file (which could be generated by an assembler), but for now
    // just hard-code the instructions here.
    // You can use Ripes to generate the bytes for the instructions you'd like
    // to run.

    always_comb
      case(addr)
        32'h0:  instr = 32'h00000013; // This is a NOP instruction (aka addi, x0, x0, 0)
        32'h4:  instr = 32'h001000b3; // Erase memory addy in x1 (aka addi x1, x0, x1)
        32'h8:  instr = 32'h00408093; // Adds 4 to register's self (addi x1, x1, 4)
        32'hc:  instr = 32'h00208133; // add x2 x1 x2 
        32'h10: instr = 32'h00108093; // Adds 1 to register's self (addi x1, x1, 1)
		32'h14: instr = 32'hfff08093; // addi x1 x1 -1
		32'h18: instr = 32'h001170b3; // and x1 x2 x1
		32'h1c: instr = 32'h001160b3; // or x1 x2 x1
		32'h20: instr = 32'h001140b3; // xor x1 x2 x1
		32'h24: instr = 32'h001120b3; //slt x1 x2 x1
		32'h28: instr = 32'h001130b3; // sltu x1 x2 x1
		32'h2c: instr = 32'h001110b3; // sll x1 x2 x1
		32'h30: instr = 32'h001150b3; // srl x1 x2 x1
		32'h34: instr = 32'h001100b3; // sub x1, x2, x1
		32'h38: instr = 32'h401150b3; // sra x1,x2,x1
      default: instr = 0;
    endcase

endmodule

2_alu_only/progmem_test.sv
`timescale 1ns / 1ps

module tb_progmem;

    // Testbench signals
    logic [31:0] addr;
    logic [31:0] instr;

    // Instantiate the program memory module
    progmem dut (
        .addr(addr),
        .instr(instr)
    );

    // Test sequence
    initial begin
		// Save all of the simulation signals to a file
        $dumpfile("progmem.vcd");
		$dumpvars(0, dut); // Dump all of the signals in the DUT

	
        // Initialize the address
        addr = 32'h0;
        #10; // Wait for combinational logic to settle
        check_instruction(addr, 32'h00000013);

        addr = 32'h4;
        #10;
        check_instruction(addr, 32'h001000b3);

        addr = 32'h8;
        #10;
        check_instruction(addr, 32'h00408093);

        addr = 32'hc;
        #10;
        check_instruction(addr, 32'h00208133);
		
		addr = 32'h10;
        #10;
        check_instruction(addr, 32'h00108093);
		
		addr = 32'h14;
        #10;
        check_instruction(addr, 32'hfff08093);
		
		addr = 32'h18;
        #10;
        check_instruction(addr, 32'h001170b3);
		
		addr = 32'h1c;
        #10;
        check_instruction(addr, 32'h001160b3);
		
		addr = 32'h20;
        #10;
        check_instruction(addr, 32'h001140b3);
		
		addr = 32'h24;
        #10;
        check_instruction(addr, 32'h001120b3);
		
		addr = 32'h28;
        #10;
        check_instruction(addr, 32'h001130b3);
		
		addr = 32'h2c;
        #10;
        check_instruction(addr, 32'h001110b3);
		
		addr = 32'h30;
        #10;
        check_instruction(addr, 32'h001150b3);
		
		addr = 32'h34;
        #10;
        check_instruction(addr, 32'h001100b3);

        addr = 32'h38;
        #10;
        check_instruction(addr, 32'h401150b3);

        // Check an address that should default to 0
        addr = 32'h3C;
        #10;
        check_instruction(addr, 32'h00000000);

        // Finish the simulation
        $finish;
    end

    // Task to check if the instruction matches the expected value
    task check_instruction(input logic [31:0] address, input logic [31:0] expected_instr);
        begin
            if (instr !== expected_instr) begin
                $error("Mismatch at address %h: expected %h, got %h", address, expected_instr, instr);
            end else begin
                $display("Match at address %h: expected %h, got %h", address, expected_instr, instr);
            end
        end
    endtask

endmodule

2_alu_only_resubmit/progmem.vcd
$date
	Thu Apr 11 22:16:00 2024
$end
$version
	Icarus Verilog
$end
$timescale
	1ps
$end
$scope module tb_progmem $end
$scope module dut $end
$var wire 32 ! addr [31:0] $end
$var reg 32 " instr [31:0] $end
$upscope $end
$upscope $end
$enddefinitions $end
$comment Show the parameter values. $end
$dumpall
$end
#0
$dumpvars
b10011 "
b0 !
$end
#10000
b100000000000010110011 "
b100 !
#20000
b10000001000000010010011 "
b1000 !
#30000
b1000001000000100110011 "
b1100 !
#40000
b100001000000010010011 "
b10000 !
#50000
b11111111111100001000000010010011 "
b10100 !
#60000
b100010111000010110011 "
b11000 !
#70000
b100010110000010110011 "
b11100 !
#80000
b100010100000010110011 "
b100000 !
#90000
b100010010000010110011 "
b100100 !
#100000
b100010011000010110011 "
b101000 !
#110000
b100010001000010110011 "
b101100 !
#120000
b100010101000010110011 "
b110000 !
#130000
b100010000000010110011 "
b110100 !
#140000
b1000000000100010101000010110011 "
b111000 !
#150000
b0 "
b111100 !
