3_memory/pc.sv
// Program counter
module pc(input logic clk,
          input logic reset,
          output logic[31:0] addr);
		
  logic[31:0] counter;
  
  always_ff @(posedge clk) begin
	if (reset) begin
		counter <= 0;
		end
	else begin
		counter <= counter + 4;
	end
  end
	
	assign addr = counter;

endmodule

3_memory_resumbit/pc_test.sv
`timescale 1ns/1ns // 1 tick is 1ns; use 1ns resolution (since we're not simulating wire delays or anything)

// Testbench for program counter
module pc_test;

// Declare the signals that will connect to our device under test (DUT)
  logic clk = 0;
  logic reset;
  logic[31:0] addr;
  
  // Instantiate and connect the DUT
  pc dut(
		.clk(clk),
        .reset(reset),
        .addr(addr));
  
  // Create the clock signal
  always #5 clk = ~clk;

  // Now run the test!
  initial begin
    // Dump all of the signals in the design to the VCD file which we can view with GTKwave
    $dumpfile("pc.vcd");
    $dumpvars(0, dut); // Dump all of the signals in the DUT


    $display("Beginning of pc test...");

    $display("(reset asserted)" );
    reset = 1;
    #27; // Wait for a few clock cycles

    // Check that the counter is reset correctly 
    assert(addr == 0) else $error("Counter not reset: expected 0 but got %d !", addr);

    $display("(reset released)" );
    reset = 0;

    @(posedge clk); // Wait for the next rising edge
    @(negedge clk); // and a little past so we have the values

    // Check that the counter has incremented
    assert(addr == 4) else $error("Counter did not increment: expected 4 but got %d !", addr);

    // We could keep checking other things here; instead we'll just wait for a microsecond
    // so that the waveform captures a good bit of time.
    #1000

    $display("Test complete!");
    $finish; // End the simulation (even though the clock is still going
  end

endmodule

2_alu_only/pc.vcd
$date
	Wed Apr 24 14:20:34 2024
$end
$version
	Icarus Verilog
$end
$timescale
	1ns
$end
$scope module pc_test $end
$scope module dut $end
$var wire 32 ! addr [31:0] $end
$var wire 1 " clk $end
$var wire 1 # reset $end
$var reg 32 $ counter [31:0] $end
$upscope $end
$upscope $end
$enddefinitions $end
$comment Show the parameter values. $end
$dumpall
$end
#0
$dumpvars
bx $
1#
0"
bx !
$end
#5
b0 !
b0 $
1"
#10
0"
#15
1"
#20
0"
#25
1"
#27
0#
#30
0"
#35
b100 !
b100 $
1"
#40
0"
#45
b1000 !
b1000 $
1"
#50
0"
#55
b1100 !
b1100 $
1"
#60
0"
#65
b10000 !
b10000 $
1"
#70
0"
#75
b10100 !
b10100 $
1"
#80
0"
#85
b11000 !
b11000 $
1"
#90
0"
#95
b11100 !
b11100 $
1"
#100
0"
#105
b100000 !
b100000 $
1"
#110
0"
#115
b100100 !
b100100 $
1"
#120
0"
#125
b101000 !
b101000 $
1"
#130
0"
#135
b101100 !
b101100 $
1"
#140
0"
#145
b110000 !
b110000 $
1"
#150
0"
#155
b110100 !
b110100 $
1"
#160
0"
#165
b111000 !
b111000 $
1"
#170
0"
#175
b111100 !
b111100 $
1"
#180
0"
#185
b1000000 !
b1000000 $
1"
#190
0"
#195
b1000100 !
b1000100 $
1"
#200
0"
#205
b1001000 !
b1001000 $
1"
#210
0"
#215
b1001100 !
b1001100 $
1"
#220
0"
#225
b1010000 !
b1010000 $
1"
#230
0"
#235
b1010100 !
b1010100 $
1"
#240
0"
#245
b1011000 !
b1011000 $
1"
#250
0"
#255
b1011100 !
b1011100 $
1"
#260
0"
#265
b1100000 !
b1100000 $
1"
#270
0"
#275
b1100100 !
b1100100 $
1"
#280
0"
#285
b1101000 !
b1101000 $
1"
#290
0"
#295
b1101100 !
b1101100 $
1"
#300
0"
#305
b1110000 !
b1110000 $
1"
#310
0"
#315
b1110100 !
b1110100 $
1"
#320
0"
#325
b1111000 !
b1111000 $
1"
#330
0"
#335
b1111100 !
b1111100 $
1"
#340
0"
#345
b10000000 !
b10000000 $
1"
#350
0"
#355
b10000100 !
b10000100 $
1"
#360
0"
#365
b10001000 !
b10001000 $
1"
#370
0"
#375
b10001100 !
b10001100 $
1"
#380
0"
#385
b10010000 !
b10010000 $
1"
#390
0"
#395
b10010100 !
b10010100 $
1"
#400
0"
#405
b10011000 !
b10011000 $
1"
#410
0"
#415
b10011100 !
b10011100 $
1"
#420
0"
#425
b10100000 !
b10100000 $
1"
#430
0"
#435
b10100100 !
b10100100 $
1"
#440
0"
#445
b10101000 !
b10101000 $
1"
#450
0"
#455
b10101100 !
b10101100 $
1"
#460
0"
#465
b10110000 !
b10110000 $
1"
#470
0"
#475
b10110100 !
b10110100 $
1"
#480
0"
#485
b10111000 !
b10111000 $
1"
#490
0"
#495
b10111100 !
b10111100 $
1"
#500
0"
#505
b11000000 !
b11000000 $
1"
#510
0"
#515
b11000100 !
b11000100 $
1"
#520
0"
#525
b11001000 !
b11001000 $
1"
#530
0"
#535
b11001100 !
b11001100 $
1"
#540
0"
#545
b11010000 !
b11010000 $
1"
#550
0"
#555
b11010100 !
b11010100 $
1"
#560
0"
#565
b11011000 !
b11011000 $
1"
#570
0"
#575
b11011100 !
b11011100 $
1"
#580
0"
#585
b11100000 !
b11100000 $
1"
#590
0"
#595
b11100100 !
b11100100 $
1"
#600
0"
#605
b11101000 !
b11101000 $
1"
#610
0"
#615
b11101100 !
b11101100 $
1"
#620
0"
#625
b11110000 !
b11110000 $
1"
#630
0"
#635
b11110100 !
b11110100 $
1"
#640
0"
#645
b11111000 !
b11111000 $
1"
#650
0"
#655
b11111100 !
b11111100 $
1"
#660
0"
#665
b100000000 !
b100000000 $
1"
#670
0"
#675
b100000100 !
b100000100 $
1"
#680
0"
#685
b100001000 !
b100001000 $
1"
#690
0"
#695
b100001100 !
b100001100 $
1"
#700
0"
#705
b100010000 !
b100010000 $
1"
#710
0"
#715
b100010100 !
b100010100 $
1"
#720
0"
#725
b100011000 !
b100011000 $
1"
#730
0"
#735
b100011100 !
b100011100 $
1"
#740
0"
#745
b100100000 !
b100100000 $
1"
#750
0"
#755
b100100100 !
b100100100 $
1"
#760
0"
#765
b100101000 !
b100101000 $
1"
#770
0"
#775
b100101100 !
b100101100 $
1"
#780
0"
#785
b100110000 !
b100110000 $
1"
#790
0"
#795
b100110100 !
b100110100 $
1"
#800
0"
#805
b100111000 !
b100111000 $
1"
#810
0"
#815
b100111100 !
b100111100 $
1"
#820
0"
#825
b101000000 !
b101000000 $
1"
#830
0"
#835
b101000100 !
b101000100 $
1"
#840
0"
#845
b101001000 !
b101001000 $
1"
#850
0"
#855
b101001100 !
b101001100 $
1"
#860
0"
#865
b101010000 !
b101010000 $
1"
#870
0"
#875
b101010100 !
b101010100 $
1"
#880
0"
#885
b101011000 !
b101011000 $
1"
#890
0"
#895
b101011100 !
b101011100 $
1"
#900
0"
#905
b101100000 !
b101100000 $
1"
#910
0"
#915
b101100100 !
b101100100 $
1"
#920
0"
#925
b101101000 !
b101101000 $
1"
#930
0"
#935
b101101100 !
b101101100 $
1"
#940
0"
#945
b101110000 !
b101110000 $
1"
#950
0"
#955
b101110100 !
b101110100 $
1"
#960
0"
#965
b101111000 !
b101111000 $
1"
#970
0"
#975
b101111100 !
b101111100 $
1"
#980
0"
#985
b110000000 !
b110000000 $
1"
#990
0"
#995
b110000100 !
b110000100 $
1"
#1000
0"
#1005
b110001000 !
b110001000 $
1"
#1010
0"
#1015
b110001100 !
b110001100 $
1"
#1020
0"
#1025
b110010000 !
b110010000 $
1"
#1030
0"
#1035
b110010100 !
b110010100 $
1"
