3_memory_4_updates/immextend.sv
module immextend(
    input logic [31:0] instr,
    output logic [31:0] imm32
);

    // Define constants for instruction opcodes for clarity
    localparam logic [6:0] OPCODE_I_TYPE_ALU = 7'b0010011, // ALU with immediates (e.g., addi)
                           OPCODE_L_TYPE = 7'b0000011,     // Loads
                           OPCODE_S_TYPE = 7'b0100011,     // Stores
                           OPCODE_B_TYPE = 7'b1100011,     // Branches
                           OPCODE_JALR = 7'b1100111,       // JALR
                           OPCODE_JAL = 7'b1101111;        // JAL

    // Immediate extraction and sign-extension
    assign imm32 = (instr[6:0] == OPCODE_I_TYPE_ALU) ? {{20{instr[31]}}, instr[31:20]} :  // I-Type ALU
                   (instr[6:0] == OPCODE_L_TYPE) ? {{20{instr[31]}}, instr[31:20]} :     // L-Type Load
                   (instr[6:0] == OPCODE_S_TYPE) ? {{20{instr[31]}}, instr[31:25], instr[11:7]} : // S-Type Store
                   (instr[6:0] == OPCODE_B_TYPE) ? {{19{instr[31]}}, instr[31], instr[7], instr[30:25], instr[11:8], 1'b0} : // B-Type Branch
                   (instr[6:0] == OPCODE_JALR) ? {{20{instr[31]}}, instr[31:20]} :   // JALR
                   (instr[6:0] == OPCODE_JAL) ? {{11{instr[31]}}, instr[31], instr[19:12], instr[20], instr[30:21], 1'b0} :  // JAL
                   32'b0;  // Zero for unsupported types

endmodule

3_memory_4_updates/immextend_test.sv
`timescale 1ns / 1ps

module tb_immextend;

    // Testbench signals
    logic [31:0] instr;
    logic [31:0] imm32;
    logic [31:0] expected_imm;


    // Instantiate the immextend module
    immextend dut (
        .instr(instr),
        .imm32(imm32)
    );

	// Function to check if the results match
    function void check_result(string description, logic [31:0] actual, logic [31:0] expected);
        if (actual != expected) begin
            $display("%s FAILED: Expected %h, Got %h", description, expected, actual);
        end else begin
            $display("%s PASSED", description);
        end
    endfunction
	
    // Test sequence
    initial begin
        // Dump all of the signals in the design to the VCD file for visualization
        $dumpfile("immextend.vcd");
        $dumpvars(0, tb_immextend); // Dump all signals in the testbench

		// Initialize the instruction signal
        instr = 0;

        // Test Case 1: I-Type ALU (addi)
        instr = 32'h40000293;  // addi x5, x0, 1024 (0x400 is 1024 in decimal)
        #10;
        check_result("I-Type ALU Immediate Test", imm32, 32'h00000400);

        // Test Case 2: L-Type Load (lw)
        instr = 32'h00012303;  // lw x6, 0(x2)
        #10;
        check_result("L-Type Load Immediate Test", imm32, 32'h00000000);

        // Test Case 3: S-Type Store (sw)
        instr = 32'h02112023;  // sw x1, 32(x2) (0x020 offset)
        #10;
        check_result("S-Type Store Immediate Test", imm32, 32'h00000020);  // -32 in decimal, sign-extended

        // Test Case 4: B-Type Branch (beq)
        instr = 32'h00000463;  // beq x0, x0, 8 (branch forward 8 bytes)
        #10;
        check_result("B-Type Branch Immediate Test", imm32, 32'h00000008);

        // Test Case 5: JALR
        instr = 32'h00008067;  // jalr x1, x0, 0
        #10;
        check_result("JALR Immediate Test", imm32, 32'h00000000);

        // Test Case 6: JAL
        instr = 32'h0f0000ef;  // jal x1, 240 (forward jump 240 bytes)
        #10;
        check_result("JAL Immediate Test", imm32, 32'h000000F0);

        // Test Case 7: R-Type (add)
        instr = 32'h003302B3;  // add x5, x6, x3
        #10;
        check_result("R-Type Immediate Test", imm32, 32'h00000000);  // Should be zero since R-Types have no immediates

        $finish;
    end

endmodule

3_memory_4_updates/immextend.vcd
$date
	Sat May 04 19:59:14 2024
$end
$version
	Icarus Verilog
$end
$timescale
	1ps
$end
$scope module tb_immextend $end
$var wire 32 ! imm32 [31:0] $end
$var reg 32 " instr [31:0] $end
$scope function check_result $end
$var reg 32 # actual [31:0] $end
$var reg 32 $ expected [31:0] $end
$upscope $end
$scope module dut $end
$var wire 32 % instr [31:0] $end
$var wire 32 & imm32 [31:0] $end
$var parameter 7 ' OPCODE_B_TYPE $end
$var parameter 7 ( OPCODE_I_TYPE_ALU $end
$var parameter 7 ) OPCODE_JAL $end
$var parameter 7 * OPCODE_JALR $end
$var parameter 7 + OPCODE_L_TYPE $end
$var parameter 7 , OPCODE_S_TYPE $end
$upscope $end
$upscope $end
$enddefinitions $end
$comment Show the parameter values. $end
$dumpall
b100011 ,
b11 +
b1100111 *
b1101111 )
b10011 (
b1100011 '
$end
#0
$dumpvars
b10000000000 &
b1000000000000000000001010010011 %
bx $
bx #
b1000000000000000000001010010011 "
b10000000000 !
$end
#10000
b0 !
b0 &
b10010001100000011 "
b10010001100000011 %
b10000000000 $
b10000000000 #
#20000
b100000 !
b100000 &
b10000100010010000000100011 "
b10000100010010000000100011 %
b0 $
b0 #
#30000
b1000 !
b1000 &
b10001100011 "
b10001100011 %
b100000 $
b100000 #
#40000
b0 !
b0 &
b1000000001100111 "
b1000000001100111 %
b1000 $
b1000 #
#50000
b11110000 !
b11110000 &
b1111000000000000000011101111 "
b1111000000000000000011101111 %
b0 $
b0 #
#60000
b0 !
b0 &
b1100110000001010110011 "
b1100110000001010110011 %
b11110000 $
b11110000 #
#70000
b0 $
b0 #
