3_memory_4_updates/pc.sv
// Updated Program Counter to handle branching and jumping
module pc(
    input logic clk,
    input logic reset,
    input logic load,             // Signal to load a new address
    input logic[31:0] load_value, // The new address to load
    output logic[31:0] addr
);

logic[31:0] counter;

always_ff @(posedge clk) begin
    if (reset) begin
        counter <= 0; // Reset counter to 0
    end else if (load) begin
        counter <= load_value; // Load the branch/jump address
    end else begin
        counter <= counter + 4; // Default: increment by 4
    end
end

assign addr = counter; // Output the current counter value

endmodule


/*// Program counter
module pc(input logic clk,
          input logic reset,
          output logic[31:0] addr);
		
  logic[31:0] counter;
  
  always_ff @(posedge clk) begin
	if (reset) begin
		counter <= 0;
		end
	else begin
		counter <= counter + 4;
	end
  end
	
	assign addr = counter;

endmodule*/

3_memory_4_updates/pc_test.sv
`timescale 1ns/1ns // 1 tick is 1ns; use 1ns resolution (since we're not simulating wire delays or anything)

// Testbench for program counter with branch and jump capabilities
module pc_test;

// Declare the signals that will connect to our device under test (DUT)
logic clk = 0;
logic reset;
logic load;
logic[31:0] load_value;
logic[31:0] addr;

// Instantiate and connect the DUT
pc dut(
    .clk(clk),
    .reset(reset),
    .load(load),
    .load_value(load_value),
    .addr(addr)
);

// Create the clock signal
always #5 clk = ~clk; // 100 MHz clock, 10 ns period

// Now run the test!
initial begin
    // Dump all of the signals in the design to the VCD file which we can view with GTKwave
    $dumpfile("pc.vcd");
    $dumpvars(0, pc_test); // Dump all of the signals in this test module

    $display("Beginning of pc test...");

    // Reset the program counter
    $display("(reset asserted)");
    reset = 1; load = 0; load_value = 32'h0;
    #27; // Wait for a few clock cycles

    // Check that the counter is reset correctly
    assert(addr == 0) else $error("Counter not reset: expected 0 but got %d!", addr);

    // Release reset
    $display("(reset released)");
    reset = 0;

    @(posedge clk); // Wait for the next rising edge
    @(negedge clk); // and a little past so we have the values

    // Check that the counter has incremented by 4 after reset
    assert(addr == 4) else $error("Counter did not increment: expected 4 but got %d!", addr);

    // Test the load functionality
    $display("(testing load functionality)");
    load = 1;
    load_value = 32'h1234;
    @(posedge clk);
    @(negedge clk);
    load = 0; // Ensure load is disabled after use

    // Check that the counter has loaded the value correctly
    assert(addr == 32'h1234) else $error("Load did not work: expected 1234 but got %h!", addr);

    // Continue clocking to see normal increment after load
    @(posedge clk);
    @(negedge clk);

    // Check normal increment after loaded value
    assert(addr == 32'h1238) else $error("Counter did not increment after load: expected 1238 but got %h!", addr);

    // We could keep checking other things here; instead we'll just wait for a microsecond
    // so that the waveform captures a good bit of time.
    #1000

    $display("Test complete!");
    $finish; // End the simulation
end

endmodule

/*`timescale 1ns/1ns // 1 tick is 1ns; use 1ns resolution (since we're not simulating wire delays or anything)

// Testbench for program counter
module pc_test;

// Declare the signals that will connect to our device under test (DUT)
  logic clk = 0;
  logic reset;
  logic[31:0] addr;
  
  // Instantiate and connect the DUT
  pc dut(
		.clk(clk),
        .reset(reset),
        .addr(addr));
  
  // Create the clock signal
  always #5 clk = ~clk;

  // Now run the test!
  initial begin
    // Dump all of the signals in the design to the VCD file which we can view with GTKwave
    $dumpfile("pc.vcd");
    $dumpvars(0, dut); // Dump all of the signals in the DUT


    $display("Beginning of pc test...");

    $display("(reset asserted)" );
    reset = 1;
    #27; // Wait for a few clock cycles

    // Check that the counter is reset correctly 
    assert(addr == 0) else $error("Counter not reset: expected 0 but got %d !", addr);

    $display("(reset released)" );
    reset = 0;

    @(posedge clk); // Wait for the next rising edge
    @(negedge clk); // and a little past so we have the values

    // Check that the counter has incremented
    assert(addr == 4) else $error("Counter did not increment: expected 4 but got %d !", addr);

    // We could keep checking other things here; instead we'll just wait for a microsecond
    // so that the waveform captures a good bit of time.
    #1000

    $display("Test complete!");
    $finish; // End the simulation (even though the clock is still going
  end

endmodule*/

3_memory_4_updates/pc.vcd
$date
	Thu May 09 14:05:40 2024
$end
$version
	Icarus Verilog
$end
$timescale
	1ns
$end
$scope module pc_test $end
$var wire 32 ! addr [31:0] $end
$var reg 1 " clk $end
$var reg 1 # load $end
$var reg 32 $ load_value [31:0] $end
$var reg 1 % reset $end
$scope module dut $end
$var wire 32 & addr [31:0] $end
$var wire 1 " clk $end
$var wire 1 # load $end
$var wire 32 ' load_value [31:0] $end
$var wire 1 % reset $end
$var reg 32 ( counter [31:0] $end
$upscope $end
$upscope $end
$enddefinitions $end
$comment Show the parameter values. $end
$dumpall
$end
#0
$dumpvars
bx (
b0 '
bx &
1%
b0 $
0#
0"
bx !
$end
#5
b0 !
b0 &
b0 (
1"
#10
0"
#15
1"
#20
0"
#25
1"
#27
0%
#30
0"
#35
b100 !
b100 &
b100 (
1"
#40
b1001000110100 $
b1001000110100 '
1#
0"
#45
b1001000110100 !
b1001000110100 &
b1001000110100 (
1"
#50
0#
0"
#55
b1001000111000 !
b1001000111000 &
b1001000111000 (
1"
#60
0"
#65
b1001000111100 !
b1001000111100 &
b1001000111100 (
1"
#70
0"
#75
b1001001000000 !
b1001001000000 &
b1001001000000 (
1"
#80
0"
#85
b1001001000100 !
b1001001000100 &
b1001001000100 (
1"
#90
0"
#95
b1001001001000 !
b1001001001000 &
b1001001001000 (
1"
#100
0"
#105
b1001001001100 !
b1001001001100 &
b1001001001100 (
1"
#110
0"
#115
b1001001010000 !
b1001001010000 &
b1001001010000 (
1"
#120
0"
#125
b1001001010100 !
b1001001010100 &
b1001001010100 (
1"
#130
0"
#135
b1001001011000 !
b1001001011000 &
b1001001011000 (
1"
#140
0"
#145
b1001001011100 !
b1001001011100 &
b1001001011100 (
1"
#150
0"
#155
b1001001100000 !
b1001001100000 &
b1001001100000 (
1"
#160
0"
#165
b1001001100100 !
b1001001100100 &
b1001001100100 (
1"
#170
0"
#175
b1001001101000 !
b1001001101000 &
b1001001101000 (
1"
#180
0"
#185
b1001001101100 !
b1001001101100 &
b1001001101100 (
1"
#190
0"
#195
b1001001110000 !
b1001001110000 &
b1001001110000 (
1"
#200
0"
#205
b1001001110100 !
b1001001110100 &
b1001001110100 (
1"
#210
0"
#215
b1001001111000 !
b1001001111000 &
b1001001111000 (
1"
#220
0"
#225
b1001001111100 !
b1001001111100 &
b1001001111100 (
1"
#230
0"
#235
b1001010000000 !
b1001010000000 &
b1001010000000 (
1"
#240
0"
#245
b1001010000100 !
b1001010000100 &
b1001010000100 (
1"
#250
0"
#255
b1001010001000 !
b1001010001000 &
b1001010001000 (
1"
#260
0"
#265
b1001010001100 !
b1001010001100 &
b1001010001100 (
1"
#270
0"
#275
b1001010010000 !
b1001010010000 &
b1001010010000 (
1"
#280
0"
#285
b1001010010100 !
b1001010010100 &
b1001010010100 (
1"
#290
0"
#295
b1001010011000 !
b1001010011000 &
b1001010011000 (
1"
#300
0"
#305
b1001010011100 !
b1001010011100 &
b1001010011100 (
1"
#310
0"
#315
b1001010100000 !
b1001010100000 &
b1001010100000 (
1"
#320
0"
#325
b1001010100100 !
b1001010100100 &
b1001010100100 (
1"
#330
0"
#335
b1001010101000 !
b1001010101000 &
b1001010101000 (
1"
#340
0"
#345
b1001010101100 !
b1001010101100 &
b1001010101100 (
1"
#350
0"
#355
b1001010110000 !
b1001010110000 &
b1001010110000 (
1"
#360
0"
#365
b1001010110100 !
b1001010110100 &
b1001010110100 (
1"
#370
0"
#375
b1001010111000 !
b1001010111000 &
b1001010111000 (
1"
#380
0"
#385
b1001010111100 !
b1001010111100 &
b1001010111100 (
1"
#390
0"
#395
b1001011000000 !
b1001011000000 &
b1001011000000 (
1"
#400
0"
#405
b1001011000100 !
b1001011000100 &
b1001011000100 (
1"
#410
0"
#415
b1001011001000 !
b1001011001000 &
b1001011001000 (
1"
#420
0"
#425
b1001011001100 !
b1001011001100 &
b1001011001100 (
1"
#430
0"
#435
b1001011010000 !
b1001011010000 &
b1001011010000 (
1"
#440
0"
#445
b1001011010100 !
b1001011010100 &
b1001011010100 (
1"
#450
0"
#455
b1001011011000 !
b1001011011000 &
b1001011011000 (
1"
#460
0"
#465
b1001011011100 !
b1001011011100 &
b1001011011100 (
1"
#470
0"
#475
b1001011100000 !
b1001011100000 &
b1001011100000 (
1"
#480
0"
#485
b1001011100100 !
b1001011100100 &
b1001011100100 (
1"
#490
0"
#495
b1001011101000 !
b1001011101000 &
b1001011101000 (
1"
#500
0"
#505
b1001011101100 !
b1001011101100 &
b1001011101100 (
1"
#510
0"
#515
b1001011110000 !
b1001011110000 &
b1001011110000 (
1"
#520
0"
#525
b1001011110100 !
b1001011110100 &
b1001011110100 (
1"
#530
0"
#535
b1001011111000 !
b1001011111000 &
b1001011111000 (
1"
#540
0"
#545
b1001011111100 !
b1001011111100 &
b1001011111100 (
1"
#550
0"
#555
b1001100000000 !
b1001100000000 &
b1001100000000 (
1"
#560
0"
#565
b1001100000100 !
b1001100000100 &
b1001100000100 (
1"
#570
0"
#575
b1001100001000 !
b1001100001000 &
b1001100001000 (
1"
#580
0"
#585
b1001100001100 !
b1001100001100 &
b1001100001100 (
1"
#590
0"
#595
b1001100010000 !
b1001100010000 &
b1001100010000 (
1"
#600
0"
#605
b1001100010100 !
b1001100010100 &
b1001100010100 (
1"
#610
0"
#615
b1001100011000 !
b1001100011000 &
b1001100011000 (
1"
#620
0"
#625
b1001100011100 !
b1001100011100 &
b1001100011100 (
1"
#630
0"
#635
b1001100100000 !
b1001100100000 &
b1001100100000 (
1"
#640
0"
#645
b1001100100100 !
b1001100100100 &
b1001100100100 (
1"
#650
0"
#655
b1001100101000 !
b1001100101000 &
b1001100101000 (
1"
#660
0"
#665
b1001100101100 !
b1001100101100 &
b1001100101100 (
1"
#670
0"
#675
b1001100110000 !
b1001100110000 &
b1001100110000 (
1"
#680
0"
#685
b1001100110100 !
b1001100110100 &
b1001100110100 (
1"
#690
0"
#695
b1001100111000 !
b1001100111000 &
b1001100111000 (
1"
#700
0"
#705
b1001100111100 !
b1001100111100 &
b1001100111100 (
1"
#710
0"
#715
b1001101000000 !
b1001101000000 &
b1001101000000 (
1"
#720
0"
#725
b1001101000100 !
b1001101000100 &
b1001101000100 (
1"
#730
0"
#735
b1001101001000 !
b1001101001000 &
b1001101001000 (
1"
#740
0"
#745
b1001101001100 !
b1001101001100 &
b1001101001100 (
1"
#750
0"
#755
b1001101010000 !
b1001101010000 &
b1001101010000 (
1"
#760
0"
#765
b1001101010100 !
b1001101010100 &
b1001101010100 (
1"
#770
0"
#775
b1001101011000 !
b1001101011000 &
b1001101011000 (
1"
#780
0"
#785
b1001101011100 !
b1001101011100 &
b1001101011100 (
1"
#790
0"
#795
b1001101100000 !
b1001101100000 &
b1001101100000 (
1"
#800
0"
#805
b1001101100100 !
b1001101100100 &
b1001101100100 (
1"
#810
0"
#815
b1001101101000 !
b1001101101000 &
b1001101101000 (
1"
#820
0"
#825
b1001101101100 !
b1001101101100 &
b1001101101100 (
1"
#830
0"
#835
b1001101110000 !
b1001101110000 &
b1001101110000 (
1"
#840
0"
#845
b1001101110100 !
b1001101110100 &
b1001101110100 (
1"
#850
0"
#855
b1001101111000 !
b1001101111000 &
b1001101111000 (
1"
#860
0"
#865
b1001101111100 !
b1001101111100 &
b1001101111100 (
1"
#870
0"
#875
b1001110000000 !
b1001110000000 &
b1001110000000 (
1"
#880
0"
#885
b1001110000100 !
b1001110000100 &
b1001110000100 (
1"
#890
0"
#895
b1001110001000 !
b1001110001000 &
b1001110001000 (
1"
#900
0"
#905
b1001110001100 !
b1001110001100 &
b1001110001100 (
1"
#910
0"
#915
b1001110010000 !
b1001110010000 &
b1001110010000 (
1"
#920
0"
#925
b1001110010100 !
b1001110010100 &
b1001110010100 (
1"
#930
0"
#935
b1001110011000 !
b1001110011000 &
b1001110011000 (
1"
#940
0"
#945
b1001110011100 !
b1001110011100 &
b1001110011100 (
1"
#950
0"
#955
b1001110100000 !
b1001110100000 &
b1001110100000 (
1"
#960
0"
#965
b1001110100100 !
b1001110100100 &
b1001110100100 (
1"
#970
0"
#975
b1001110101000 !
b1001110101000 &
b1001110101000 (
1"
#980
0"
#985
b1001110101100 !
b1001110101100 &
b1001110101100 (
1"
#990
0"
#995
b1001110110000 !
b1001110110000 &
b1001110110000 (
1"
#1000
0"
#1005
b1001110110100 !
b1001110110100 &
b1001110110100 (
1"
#1010
0"
#1015
b1001110111000 !
b1001110111000 &
b1001110111000 (
1"
#1020
0"
#1025
b1001110111100 !
b1001110111100 &
b1001110111100 (
1"
#1030
0"
#1035
b1001111000000 !
b1001111000000 &
b1001111000000 (
1"
#1040
0"
#1045
b1001111000100 !
b1001111000100 &
b1001111000100 (
1"
#1050
0"
#1055
b1001111001000 !
b1001111001000 &
b1001111001000 (
1"
